openai_tts/__init__.py
openai_tts/config.py
openai_tts/exceptions.py
openai_tts/utils.py
openai_tts/providers/__init__.py
openai_tts/providers/base.py
openai_tts/providers/openai.py
openai_tts-2.0.0.dist-info/LICENSE
openai_tts-2.0.0.dist-info/METADATA
openai_tts-2.0.0.dist-info/WHEEL
openai_tts-2.0.0.dist-info/top_level.txt
openai_tts-2.0.0.dist-info/RECORD
